belay/__init__.py
belay/__main__.py
belay/_minify.py
belay/cli/__init__.py
belay/cli/add.py
belay/cli/cache.py
belay/cli/clean.py
belay/cli/common.py
belay/cli/exec.py
belay/cli/info.py
belay/cli/install.py
belay/cli/latency.py
belay/cli/main.py
belay/cli/new.py
belay/cli/new_template/README.md
belay/cli/new_template/main.py
belay/cli/new_template/packagename/__init__.py
belay/cli/new_template/pyproject.toml
belay/cli/questionary_ext.py
belay/cli/run.py
belay/cli/select.py
belay/cli/sync.py
belay/cli/terminal.py
belay/cli/update.py
belay/device.py
belay/device_meta.py
belay/device_support.py
belay/device_sync_support.py
belay/exceptions.py
belay/executers.py
belay/hash.py
belay/helpers.py
belay/inspect.py
belay/nativemodule_fnv1a32/__init__.py
belay/nativemodule_fnv1a32/mpy1.22-armv6m.mpy
belay/nativemodule_fnv1a32/mpy1.22-armv7emdp.mpy
belay/nativemodule_fnv1a32/mpy1.22-armv7emsp.mpy
belay/nativemodule_fnv1a32/mpy1.22-armv7m.mpy
belay/nativemodule_fnv1a32/mpy1.22-x64.mpy
belay/nativemodule_fnv1a32/mpy1.22-x86.mpy
belay/nativemodule_fnv1a32/mpy1.22-xtensa.mpy
belay/nativemodule_fnv1a32/mpy1.22-xtensawin.mpy
belay/nativemodule_fnv1a32/mpy1.23-armv6m.mpy
belay/nativemodule_fnv1a32/mpy1.23-armv7emdp.mpy
belay/nativemodule_fnv1a32/mpy1.23-armv7emsp.mpy
belay/nativemodule_fnv1a32/mpy1.23-armv7m.mpy
belay/nativemodule_fnv1a32/mpy1.23-x64.mpy
belay/nativemodule_fnv1a32/mpy1.23-x86.mpy
belay/nativemodule_fnv1a32/mpy1.23-xtensa.mpy
belay/nativemodule_fnv1a32/mpy1.23-xtensawin.mpy
belay/nativemodule_fnv1a32/mpy1.24-armv6m.mpy
belay/nativemodule_fnv1a32/mpy1.24-armv7emdp.mpy
belay/nativemodule_fnv1a32/mpy1.24-armv7emsp.mpy
belay/nativemodule_fnv1a32/mpy1.24-armv7m.mpy
belay/nativemodule_fnv1a32/mpy1.24-x64.mpy
belay/nativemodule_fnv1a32/mpy1.24-x86.mpy
belay/nativemodule_fnv1a32/mpy1.24-xtensa.mpy
belay/nativemodule_fnv1a32/mpy1.24-xtensawin.mpy
belay/nativemodule_fnv1a32/mpy1.25-armv6m.mpy
belay/nativemodule_fnv1a32/mpy1.25-armv7emdp.mpy
belay-0.30.0.dist-info/LICENSE
belay-0.30.0.dist-info/METADATA
belay-0.30.0.dist-info/WHEEL
belay-0.30.0.dist-info/entry_points.txt
belay-0.30.0.dist-info/RECORD
