Metadata-Version: 2.1
Name: belay
Version: 0.30.0
Summary: 
Home-page: https://github.com/BrianPugh/belay
License: Apache-2.0
Author: Brian Pugh
Requires-Python: >=3.9
Classifier: License :: OSI Approved :: Apache Software License
Classifier: Programming Language :: Python :: 3
Classifier: Programming Language :: Python :: 3.9
Classifier: Programming Language :: Python :: 3.10
Classifier: Programming Language :: Python :: 3.11
Classifier: Programming Language :: Python :: 3.12
Classifier: Programming Language :: Python :: 3.13
Requires-Dist: attrs (>=21.0.0)
Requires-Dist: autoregistry (>=0.10.1)
Requires-Dist: cyclopts (>=3.22.0)
Requires-Dist: fsspec[http] (>=2022.11.0)
Requires-Dist: gitpython (>=3.1.30)
Requires-Dist: packaging (>=20.4)
Requires-Dist: pathspec (>=0.10.3)
Requires-Dist: pydantic (>=2.0.0)
Requires-Dist: pyserial (>=3.1)
Requires-Dist: questionary (>=2.0.0)
Requires-Dist: requests (>=2.28.1)
Requires-Dist: tenacity (>=8.0.0)
Requires-Dist: tomli (>=2.0.1)
Requires-Dist: tomlkit (>=0.11.0)
Requires-Dist: typing-extensions (>=4.5.0)
Project-URL: Repository, https://github.com/BrianPugh/belay
